{
  "setId": "BIGT-A2-LS-S04",
  "cefr": "A2",
  "skill": "listening",
  "provider": "google",
  "generatedAt": "2026-06-26T00:38:26.809Z",
  "items": [
    {
      "questionId": "BIGT-A2-LS-S04-Q001",
      "audioId": "BIGT-A2-LS-S04-A001",
      "audioFile": "BIGT-A2-LS-S04-A001.mp3",
      "audioPath": "/audio/listening/a2/set-04/BIGT-A2-LS-S04-A001.mp3",
      "speaker": "male_01",
      "voiceId": "id-ID-Standard-D",
      "status": "generated",
      "fileSizeBytes": 113664,
      "transcriptHash": "4eec0adae0fb771afa29b8a603c44bebc9ae64419819eaffed3ba65fa6ffb093",
      "generatedAt": "2026-06-26T00:37:56.246Z"
    },
    {
      "questionId": "BIGT-A2-LS-S04-Q002",
      "audioId": "BIGT-A2-LS-S04-A002",
      "audioFile": "BIGT-A2-LS-S04-A002.mp3",
      "audioPath": "/audio/listening/a2/set-04/BIGT-A2-LS-S04-A002.mp3",
      "speaker": "male_01_female_01",
      "voiceId": "id-ID-Standard-A",
      "status": "generated",
      "fileSizeBytes": 104064,
      "transcriptHash": "306864032b029b12bbd7b1be8149c886d6dc567f2f49ba8a59d523804733c4f5",
      "generatedAt": "2026-06-26T00:37:57.124Z"
    },
    {
      "questionId": "BIGT-A2-LS-S04-Q003",
      "audioId": "BIGT-A2-LS-S04-A003",
      "audioFile": "BIGT-A2-LS-S04-A003.mp3",
      "audioPath": "/audio/listening/a2/set-04/BIGT-A2-LS-S04-A003.mp3",
      "speaker": "female_02",
      "voiceId": "id-ID-Standard-A",
      "status": "generated",
      "fileSizeBytes": 120960,
      "transcriptHash": "fea6894e612c64ee28e7015197dc087cf22e5e362e847754a949b605c95e1a4e",
      "generatedAt": "2026-06-26T00:37:57.854Z"
    },
    {
      "questionId": "BIGT-A2-LS-S04-Q004",
      "audioId": "BIGT-A2-LS-S04-A004",
      "audioFile": "BIGT-A2-LS-S04-A004.mp3",
      "audioPath": "/audio/listening/a2/set-04/BIGT-A2-LS-S04-A004.mp3",
      "speaker": "male_01_male_01",
      "voiceId": "id-ID-Standard-A",
      "status": "generated",
      "fileSizeBytes": 124224,
      "transcriptHash": "90949a010d226c49ea68155f2bcffcacb843c1d46fa940d7ab24f76ba56205da",
      "generatedAt": "2026-06-26T00:37:58.674Z"
    },
    {
      "questionId": "BIGT-A2-LS-S04-Q005",
      "audioId": "BIGT-A2-LS-S04-A005",
      "audioFile": "BIGT-A2-LS-S04-A005.mp3",
      "audioPath": "/audio/listening/a2/set-04/BIGT-A2-LS-S04-A005.mp3",
      "speaker": "male_01",
      "voiceId": "id-ID-Standard-D",
      "status": "generated",
      "fileSizeBytes": 105408,
      "transcriptHash": "90c3f2c21c8964b1c894e368f85da8847b444429b0539ed78c467d3b96faef8d",
      "generatedAt": "2026-06-26T00:37:59.373Z"
    },
    {
      "questionId": "BIGT-A2-LS-S04-Q006",
      "audioId": "BIGT-A2-LS-S04-A006",
      "audioFile": "BIGT-A2-LS-S04-A006.mp3",
      "audioPath": "/audio/listening/a2/set-04/BIGT-A2-LS-S04-A006.mp3",
      "speaker": "male_01",
      "voiceId": "id-ID-Standard-D",
      "status": "generated",
      "fileSizeBytes": 109632,
      "transcriptHash": "86488fc7ba4776b61449c5d6af60c3704e18f7e79b8bed468a311d5d7564b02a",
      "generatedAt": "2026-06-26T00:38:00.214Z"
    },
    {
      "questionId": "BIGT-A2-LS-S04-Q007",
      "audioId": "BIGT-A2-LS-S04-A007",
      "audioFile": "BIGT-A2-LS-S04-A007.mp3",
      "audioPath": "/audio/listening/a2/set-04/BIGT-A2-LS-S04-A007.mp3",
      "speaker": "female_01_female_02",
      "voiceId": "id-ID-Standard-A",
      "status": "generated",
      "fileSizeBytes": 97344,
      "transcriptHash": "b490590be7b5585da340f4b4b9ea01dbe6331631feb12f8bcf99f31811632885",
      "generatedAt": "2026-06-26T00:38:00.971Z"
    },
    {
      "questionId": "BIGT-A2-LS-S04-Q008",
      "audioId": "BIGT-A2-LS-S04-A008",
      "audioFile": "BIGT-A2-LS-S04-A008.mp3",
      "audioPath": "/audio/listening/a2/set-04/BIGT-A2-LS-S04-A008.mp3",
      "speaker": "female_02",
      "voiceId": "id-ID-Standard-A",
      "status": "generated",
      "fileSizeBytes": 117312,
      "transcriptHash": "ac63312447ff38d1ee107663d77b78cd959f74d807af105e57f9aca1d04121c4",
      "generatedAt": "2026-06-26T00:38:01.802Z"
    },
    {
      "questionId": "BIGT-A2-LS-S04-Q009",
      "audioId": "BIGT-A2-LS-S04-A009",
      "audioFile": "BIGT-A2-LS-S04-A009.mp3",
      "audioPath": "/audio/listening/a2/set-04/BIGT-A2-LS-S04-A009.mp3",
      "speaker": "female_02",
      "voiceId": "id-ID-Standard-A",
      "status": "generated",
      "fileSizeBytes": 104064,
      "transcriptHash": "eb522ed03e2e61c0c65952a85562ff399d7ceac33be63db66f92a7e407e3f870",
      "generatedAt": "2026-06-26T00:38:02.450Z"
    },
    {
      "questionId": "BIGT-A2-LS-S04-Q010",
      "audioId": "BIGT-A2-LS-S04-A010",
      "audioFile": "BIGT-A2-LS-S04-A010.mp3",
      "audioPath": "/audio/listening/a2/set-04/BIGT-A2-LS-S04-A010.mp3",
      "speaker": "male_02",
      "voiceId": "id-ID-Standard-D",
      "status": "generated",
      "fileSizeBytes": 105024,
      "transcriptHash": "eaebde7ceb129d3cd9e345f9439c005f53ee854d21666c64ae705d55307b22ea",
      "generatedAt": "2026-06-26T00:38:03.743Z"
    },
    {
      "questionId": "BIGT-A2-LS-S04-Q011",
      "audioId": "BIGT-A2-LS-S04-A011",
      "audioFile": "BIGT-A2-LS-S04-A011.mp3",
      "audioPath": "/audio/listening/a2/set-04/BIGT-A2-LS-S04-A011.mp3",
      "speaker": "male_01",
      "voiceId": "id-ID-Standard-D",
      "status": "generated",
      "fileSizeBytes": 84672,
      "transcriptHash": "959ff8619621e0a4721af0dcba9a48c8f9982d0f4d1c0b509db1271dcd22f687",
      "generatedAt": "2026-06-26T00:38:04.207Z"
    },
    {
      "questionId": "BIGT-A2-LS-S04-Q012",
      "audioId": "BIGT-A2-LS-S04-A012",
      "audioFile": "BIGT-A2-LS-S04-A012.mp3",
      "audioPath": "/audio/listening/a2/set-04/BIGT-A2-LS-S04-A012.mp3",
      "speaker": "male_02",
      "voiceId": "id-ID-Standard-D",
      "status": "generated",
      "fileSizeBytes": 105024,
      "transcriptHash": "33ce0fc2be97830c5dbfd255670b141b0fa38a311defbbfbd61c63ce0553925e",
      "generatedAt": "2026-06-26T00:38:04.776Z"
    },
    {
      "questionId": "BIGT-A2-LS-S04-Q013",
      "audioId": "BIGT-A2-LS-S04-A013",
      "audioFile": "BIGT-A2-LS-S04-A013.mp3",
      "audioPath": "/audio/listening/a2/set-04/BIGT-A2-LS-S04-A013.mp3",
      "speaker": "male_01",
      "voiceId": "id-ID-Standard-D",
      "status": "generated",
      "fileSizeBytes": 111360,
      "transcriptHash": "f45cd3ec50682b364e85a84daa298e3f5067b9ee4eeb3f7fd2f1dd49d753d46a",
      "generatedAt": "2026-06-26T00:38:05.238Z"
    },
    {
      "questionId": "BIGT-A2-LS-S04-Q014",
      "audioId": "BIGT-A2-LS-S04-A014",
      "audioFile": "BIGT-A2-LS-S04-A014.mp3",
      "audioPath": "/audio/listening/a2/set-04/BIGT-A2-LS-S04-A014.mp3",
      "speaker": "female_01_male_01",
      "voiceId": "id-ID-Standard-A",
      "status": "generated",
      "fileSizeBytes": 140160,
      "transcriptHash": "e03caee9d41b99eaccedbf28915ee2f3b39ca096404d37912232a5190f50066f",
      "generatedAt": "2026-06-26T00:38:06.401Z"
    },
    {
      "questionId": "BIGT-A2-LS-S04-Q015",
      "audioId": "BIGT-A2-LS-S04-A015",
      "audioFile": "BIGT-A2-LS-S04-A015.mp3",
      "audioPath": "/audio/listening/a2/set-04/BIGT-A2-LS-S04-A015.mp3",
      "speaker": "male_02",
      "voiceId": "id-ID-Standard-D",
      "status": "generated",
      "fileSizeBytes": 106944,
      "transcriptHash": "e93452b43896dbb4a691d431a9e4177a4f32d62b6e6091a8f10483c72d4c620f",
      "generatedAt": "2026-06-26T00:38:07.148Z"
    },
    {
      "questionId": "BIGT-A2-LS-S04-Q016",
      "audioId": "BIGT-A2-LS-S04-A016",
      "audioFile": "BIGT-A2-LS-S04-A016.mp3",
      "audioPath": "/audio/listening/a2/set-04/BIGT-A2-LS-S04-A016.mp3",
      "speaker": "male_01",
      "voiceId": "id-ID-Standard-D",
      "status": "generated",
      "fileSizeBytes": 104064,
      "transcriptHash": "ddbfdf34fe193dd9838b9e9ef57318fdc38f2eb87359d22947b7fb742faf88fb",
      "generatedAt": "2026-06-26T00:38:08.212Z"
    },
    {
      "questionId": "BIGT-A2-LS-S04-Q017",
      "audioId": "BIGT-A2-LS-S04-A017",
      "audioFile": "BIGT-A2-LS-S04-A017.mp3",
      "audioPath": "/audio/listening/a2/set-04/BIGT-A2-LS-S04-A017.mp3",
      "speaker": "announcer_01",
      "voiceId": "id-ID-Standard-A",
      "status": "generated",
      "fileSizeBytes": 118080,
      "transcriptHash": "29367b1168b2e88346afac2ee9b33e8dfbd494a74e622bfa8d4cc591e33b884f",
      "generatedAt": "2026-06-26T00:38:09.027Z"
    },
    {
      "questionId": "BIGT-A2-LS-S04-Q018",
      "audioId": "BIGT-A2-LS-S04-A018",
      "audioFile": "BIGT-A2-LS-S04-A018.mp3",
      "audioPath": "/audio/listening/a2/set-04/BIGT-A2-LS-S04-A018.mp3",
      "speaker": "female_01",
      "voiceId": "id-ID-Standard-A",
      "status": "generated",
      "fileSizeBytes": 109824,
      "transcriptHash": "01e3951e30ca093ca33feb499f35048494412e0621ba75533abde093be022c30",
      "generatedAt": "2026-06-26T00:38:10.355Z"
    },
    {
      "questionId": "BIGT-A2-LS-S04-Q019",
      "audioId": "BIGT-A2-LS-S04-A019",
      "audioFile": "BIGT-A2-LS-S04-A019.mp3",
      "audioPath": "/audio/listening/a2/set-04/BIGT-A2-LS-S04-A019.mp3",
      "speaker": "female_02",
      "voiceId": "id-ID-Standard-A",
      "status": "generated",
      "fileSizeBytes": 119424,
      "transcriptHash": "48ca6ee732bacb1a62682415464ce1e6000404fe02a5ccf9d59f8836ac285b7f",
      "generatedAt": "2026-06-26T00:38:11.374Z"
    },
    {
      "questionId": "BIGT-A2-LS-S04-Q020",
      "audioId": "BIGT-A2-LS-S04-A020",
      "audioFile": "BIGT-A2-LS-S04-A020.mp3",
      "audioPath": "/audio/listening/a2/set-04/BIGT-A2-LS-S04-A020.mp3",
      "speaker": "female_02",
      "voiceId": "id-ID-Standard-A",
      "status": "generated",
      "fileSizeBytes": 106368,
      "transcriptHash": "8a62304f3214ee80f687fc905eafcb96b2024ed07d038cab7bbd6f2674bf6f94",
      "generatedAt": "2026-06-26T00:38:11.852Z"
    },
    {
      "questionId": "BIGT-A2-LS-S04-Q021",
      "audioId": "BIGT-A2-LS-S04-A021",
      "audioFile": "BIGT-A2-LS-S04-A021.mp3",
      "audioPath": "/audio/listening/a2/set-04/BIGT-A2-LS-S04-A021.mp3",
      "speaker": "male_02",
      "voiceId": "id-ID-Standard-D",
      "status": "generated",
      "fileSizeBytes": 115008,
      "transcriptHash": "f9cbe9845f8cc0ec5e6ca6fd9d267b468ee819e275ca9946f9b9e6b78b7a4406",
      "generatedAt": "2026-06-26T00:38:13.064Z"
    },
    {
      "questionId": "BIGT-A2-LS-S04-Q022",
      "audioId": "BIGT-A2-LS-S04-A022",
      "audioFile": "BIGT-A2-LS-S04-A022.mp3",
      "audioPath": "/audio/listening/a2/set-04/BIGT-A2-LS-S04-A022.mp3",
      "speaker": "female_01",
      "voiceId": "id-ID-Standard-A",
      "status": "generated",
      "fileSizeBytes": 132864,
      "transcriptHash": "01980c4ea63501ebb602e578781e186ff2f76953a446f6f87222edee002c4d46",
      "generatedAt": "2026-06-26T00:38:13.963Z"
    },
    {
      "questionId": "BIGT-A2-LS-S04-Q023",
      "audioId": "BIGT-A2-LS-S04-A023",
      "audioFile": "BIGT-A2-LS-S04-A023.mp3",
      "audioPath": "/audio/listening/a2/set-04/BIGT-A2-LS-S04-A023.mp3",
      "speaker": "male_01_male_02",
      "voiceId": "id-ID-Standard-A",
      "status": "generated",
      "fileSizeBytes": 138240,
      "transcriptHash": "f57e64154d0b1a89c29dda57ec483ed9a1f0c2c08474e18a97e4dfde2107b47c",
      "generatedAt": "2026-06-26T00:38:14.857Z"
    },
    {
      "questionId": "BIGT-A2-LS-S04-Q024",
      "audioId": "BIGT-A2-LS-S04-A024",
      "audioFile": "BIGT-A2-LS-S04-A024.mp3",
      "audioPath": "/audio/listening/a2/set-04/BIGT-A2-LS-S04-A024.mp3",
      "speaker": "female_02",
      "voiceId": "id-ID-Standard-A",
      "status": "generated",
      "fileSizeBytes": 120000,
      "transcriptHash": "b0d157696b89ff0233ba719a588f211c3d45148995b8a0721571dd4e55bfc6a6",
      "generatedAt": "2026-06-26T00:38:15.653Z"
    },
    {
      "questionId": "BIGT-A2-LS-S04-Q025",
      "audioId": "BIGT-A2-LS-S04-A025",
      "audioFile": "BIGT-A2-LS-S04-A025.mp3",
      "audioPath": "/audio/listening/a2/set-04/BIGT-A2-LS-S04-A025.mp3",
      "speaker": "male_01",
      "voiceId": "id-ID-Standard-D",
      "status": "generated",
      "fileSizeBytes": 91200,
      "transcriptHash": "2e14a85e177e12a1af91c58b38e5a79fd0d87b789c2f56bf469e888f137ef9f6",
      "generatedAt": "2026-06-26T00:38:16.202Z"
    },
    {
      "questionId": "BIGT-A2-LS-S04-Q026",
      "audioId": "BIGT-A2-LS-S04-A026",
      "audioFile": "BIGT-A2-LS-S04-A026.mp3",
      "audioPath": "/audio/listening/a2/set-04/BIGT-A2-LS-S04-A026.mp3",
      "speaker": "male_01",
      "voiceId": "id-ID-Standard-D",
      "status": "generated",
      "fileSizeBytes": 98112,
      "transcriptHash": "5259d249a2ea2e72ba03f308ceda935251f97308f01218402bc249ad1943a9be",
      "generatedAt": "2026-06-26T00:38:16.979Z"
    },
    {
      "questionId": "BIGT-A2-LS-S04-Q027",
      "audioId": "BIGT-A2-LS-S04-A027",
      "audioFile": "BIGT-A2-LS-S04-A027.mp3",
      "audioPath": "/audio/listening/a2/set-04/BIGT-A2-LS-S04-A027.mp3",
      "speaker": "female_01",
      "voiceId": "id-ID-Standard-A",
      "status": "generated",
      "fileSizeBytes": 91392,
      "transcriptHash": "e7dbad5001a859119a90ad2226a9c7aeefe4a957ecdea3b5d91cf92ee0c46ecd",
      "generatedAt": "2026-06-26T00:38:17.629Z"
    },
    {
      "questionId": "BIGT-A2-LS-S04-Q028",
      "audioId": "BIGT-A2-LS-S04-A028",
      "audioFile": "BIGT-A2-LS-S04-A028.mp3",
      "audioPath": "/audio/listening/a2/set-04/BIGT-A2-LS-S04-A028.mp3",
      "speaker": "female_02",
      "voiceId": "id-ID-Standard-A",
      "status": "generated",
      "fileSizeBytes": 122496,
      "transcriptHash": "6b292b3b8bf2f0c4c69a9fa4f6759f9bfe4cd9f0382d00b070f3b8445218adbe",
      "generatedAt": "2026-06-26T00:38:18.423Z"
    },
    {
      "questionId": "BIGT-A2-LS-S04-Q029",
      "audioId": "BIGT-A2-LS-S04-A029",
      "audioFile": "BIGT-A2-LS-S04-A029.mp3",
      "audioPath": "/audio/listening/a2/set-04/BIGT-A2-LS-S04-A029.mp3",
      "speaker": "announcer_01",
      "voiceId": "id-ID-Standard-A",
      "status": "generated",
      "fileSizeBytes": 109824,
      "transcriptHash": "204bc16968194206a20a5fbd5523b7684e328b7e27bf31c4ef34196379ffd872",
      "generatedAt": "2026-06-26T00:38:19.068Z"
    },
    {
      "questionId": "BIGT-A2-LS-S04-Q030",
      "audioId": "BIGT-A2-LS-S04-A030",
      "audioFile": "BIGT-A2-LS-S04-A030.mp3",
      "audioPath": "/audio/listening/a2/set-04/BIGT-A2-LS-S04-A030.mp3",
      "speaker": "female_01",
      "voiceId": "id-ID-Standard-A",
      "status": "generated",
      "fileSizeBytes": 101184,
      "transcriptHash": "a1ee625d493eec47d3b6f62bf10bd60784fc8d70b152d515706beca4ffe345bd",
      "generatedAt": "2026-06-26T00:38:19.728Z"
    },
    {
      "questionId": "BIGT-A2-LS-S04-Q031",
      "audioId": "BIGT-A2-LS-S04-A031",
      "audioFile": "BIGT-A2-LS-S04-A031.mp3",
      "audioPath": "/audio/listening/a2/set-04/BIGT-A2-LS-S04-A031.mp3",
      "speaker": "male_01",
      "voiceId": "id-ID-Standard-D",
      "status": "generated",
      "fileSizeBytes": 81024,
      "transcriptHash": "d424fcfd626fa189417f2cb5423e46601dc52a84641889a479cb0fb43cb13024",
      "generatedAt": "2026-06-26T00:38:20.339Z"
    },
    {
      "questionId": "BIGT-A2-LS-S04-Q032",
      "audioId": "BIGT-A2-LS-S04-A032",
      "audioFile": "BIGT-A2-LS-S04-A032.mp3",
      "audioPath": "/audio/listening/a2/set-04/BIGT-A2-LS-S04-A032.mp3",
      "speaker": "female_01_female_02",
      "voiceId": "id-ID-Standard-A",
      "status": "generated",
      "fileSizeBytes": 91968,
      "transcriptHash": "524df741e37708ed1e03601e6110563462ff68676dc28436e91d08f6d97b1b40",
      "generatedAt": "2026-06-26T00:38:21.052Z"
    },
    {
      "questionId": "BIGT-A2-LS-S04-Q033",
      "audioId": "BIGT-A2-LS-S04-A033",
      "audioFile": "BIGT-A2-LS-S04-A033.mp3",
      "audioPath": "/audio/listening/a2/set-04/BIGT-A2-LS-S04-A033.mp3",
      "speaker": "male_01",
      "voiceId": "id-ID-Standard-D",
      "status": "generated",
      "fileSizeBytes": 76608,
      "transcriptHash": "106e637d95e7d8108963ef876a66285019295317c69a7e5107ab53634511beba",
      "generatedAt": "2026-06-26T00:38:21.857Z"
    },
    {
      "questionId": "BIGT-A2-LS-S04-Q034",
      "audioId": "BIGT-A2-LS-S04-A034",
      "audioFile": "BIGT-A2-LS-S04-A034.mp3",
      "audioPath": "/audio/listening/a2/set-04/BIGT-A2-LS-S04-A034.mp3",
      "speaker": "female_02",
      "voiceId": "id-ID-Standard-A",
      "status": "generated",
      "fileSizeBytes": 124992,
      "transcriptHash": "135caed1c41af5af1a154bd8b5ef0230da0df5f5b3ce8a37ad0b2737c00a4e12",
      "generatedAt": "2026-06-26T00:38:22.410Z"
    },
    {
      "questionId": "BIGT-A2-LS-S04-Q035",
      "audioId": "BIGT-A2-LS-S04-A035",
      "audioFile": "BIGT-A2-LS-S04-A035.mp3",
      "audioPath": "/audio/listening/a2/set-04/BIGT-A2-LS-S04-A035.mp3",
      "speaker": "announcer_01",
      "voiceId": "id-ID-Standard-A",
      "status": "generated",
      "fileSizeBytes": 108480,
      "transcriptHash": "9dc15b01fbbcbe39bb221008ecb0e2601f415c40ab19f729982aa7b11c601877",
      "generatedAt": "2026-06-26T00:38:23.264Z"
    },
    {
      "questionId": "BIGT-A2-LS-S04-Q036",
      "audioId": "BIGT-A2-LS-S04-A036",
      "audioFile": "BIGT-A2-LS-S04-A036.mp3",
      "audioPath": "/audio/listening/a2/set-04/BIGT-A2-LS-S04-A036.mp3",
      "speaker": "male_02",
      "voiceId": "id-ID-Standard-D",
      "status": "generated",
      "fileSizeBytes": 122496,
      "transcriptHash": "313ca9a417a573c7adda8640e67a6d9929d97c1f5d29986e006615e228cd0287",
      "generatedAt": "2026-06-26T00:38:24.068Z"
    },
    {
      "questionId": "BIGT-A2-LS-S04-Q037",
      "audioId": "BIGT-A2-LS-S04-A037",
      "audioFile": "BIGT-A2-LS-S04-A037.mp3",
      "audioPath": "/audio/listening/a2/set-04/BIGT-A2-LS-S04-A037.mp3",
      "speaker": "male_02",
      "voiceId": "id-ID-Standard-D",
      "status": "generated",
      "fileSizeBytes": 107712,
      "transcriptHash": "2b0b08147c1e0accf4c96ea5f9649dac241c34cc7a5cec11ef71674497b87738",
      "generatedAt": "2026-06-26T00:38:24.689Z"
    },
    {
      "questionId": "BIGT-A2-LS-S04-Q038",
      "audioId": "BIGT-A2-LS-S04-A038",
      "audioFile": "BIGT-A2-LS-S04-A038.mp3",
      "audioPath": "/audio/listening/a2/set-04/BIGT-A2-LS-S04-A038.mp3",
      "speaker": "male_01",
      "voiceId": "id-ID-Standard-D",
      "status": "generated",
      "fileSizeBytes": 101376,
      "transcriptHash": "fb7e14db962e45473733246494a3ae9511d4d8000f7f59cad69c56303dd98080",
      "generatedAt": "2026-06-26T00:38:25.471Z"
    },
    {
      "questionId": "BIGT-A2-LS-S04-Q039",
      "audioId": "BIGT-A2-LS-S04-A039",
      "audioFile": "BIGT-A2-LS-S04-A039.mp3",
      "audioPath": "/audio/listening/a2/set-04/BIGT-A2-LS-S04-A039.mp3",
      "speaker": "male_01",
      "voiceId": "id-ID-Standard-D",
      "status": "generated",
      "fileSizeBytes": 100800,
      "transcriptHash": "edc4aae7706c540e8cd15def322ea9919900960f98392e3ee6d430a987a49d57",
      "generatedAt": "2026-06-26T00:38:25.992Z"
    },
    {
      "questionId": "BIGT-A2-LS-S04-Q040",
      "audioId": "BIGT-A2-LS-S04-A040",
      "audioFile": "BIGT-A2-LS-S04-A040.mp3",
      "audioPath": "/audio/listening/a2/set-04/BIGT-A2-LS-S04-A040.mp3",
      "speaker": "male_01",
      "voiceId": "id-ID-Standard-D",
      "status": "generated",
      "fileSizeBytes": 103104,
      "transcriptHash": "91619a199ef8e0a78ef6c46d0028f32231bdf7cda220989779c905e2dc73c389",
      "generatedAt": "2026-06-26T00:38:26.809Z"
    }
  ]
}